getDB/__init__.py
getDB/hmdb.py
getDB-0.0.4.dist-info/LICENSE
getDB-0.0.4.dist-info/METADATA
getDB-0.0.4.dist-info/WHEEL
getDB-0.0.4.dist-info/top_level.txt
getDB-0.0.4.dist-info/RECORD
