Metadata-Version: 2.1
Name: getDB
Version: 0.0.4
Summary: This module can be used to download HMDB and KEGG database.
Home-page: https://github.com/jaspershen/getDB
Author: Xiaotao Shen
Author-email: shenxt1990@163.com
License: MIT
Platform: UNKNOWN
Classifier: Programming Language :: Python :: 3.6
Classifier: Programming Language :: Python :: 3.7
Requires-Dist: requests
Requires-Dist: pandas
Requires-Dist: bs4
Requires-Dist: numpy
